cohere/__init__.py
cohere/client.py
cohere/core/__init__.py
cohere/core/api_error.py
cohere/core/client_wrapper.py
cohere/core/datetime_utils.py
cohere/core/jsonable_encoder.py
cohere/core/remove_none_from_dict.py
cohere/environment.py
cohere/errors/__init__.py
cohere/errors/bad_request_error.py
cohere/errors/internal_server_error.py
cohere/py.typed
cohere/types/__init__.py
cohere/types/api_meta.py
cohere/types/api_meta_api_version.py
cohere/types/chat_citation.py
cohere/types/chat_citation_generation_event.py
cohere/types/chat_connector.py
cohere/types/chat_document.py
cohere/types/chat_message.py
cohere/types/chat_message_role.py
cohere/types/chat_request_citation_quality.py
cohere/types/chat_request_prompt_truncation.py
cohere/types/chat_search_queries_generation_event.py
cohere/types/chat_search_query.py
cohere/types/chat_search_result.py
cohere/types/chat_search_results_event.py
cohere/types/chat_stream_end_event.py
cohere/types/chat_stream_end_event_finish_reason.py
cohere/types/chat_stream_end_event_response.py
cohere/types/chat_stream_event.py
cohere/types/chat_stream_request_citation_quality.py
cohere/types/chat_stream_request_prompt_truncation.py
cohere/types/chat_stream_start_event.py
cohere/types/chat_text_generation_event.py
cohere/types/classify_request_examples_item.py
cohere/types/classify_request_truncate.py
cohere/types/classify_response.py
cohere/types/classify_response_classifications_item.py
cohere/types/classify_response_classifications_item_classification_type.py
cohere/types/classify_response_classifications_item_labels_value.py
cohere/types/detect_language_response.py
cohere/types/detect_language_response_results_item.py
cohere/types/detokenize_response.py
cohere/types/embed_request_truncate.py
cohere/types/embed_response.py
cohere/types/finish_reason.py
cohere/types/generate_request_return_likelihoods.py
cohere/types/generate_request_truncate.py
cohere/types/generation.py
cohere/types/generation_final_response.py
fern_cohere-0.0.33.dist-info/METADATA
fern_cohere-0.0.33.dist-info/WHEEL
fern_cohere-0.0.33.dist-info/RECORD
